txtbcGen/Model.py
txtbcGen/__init__.py
txtbcGen/reactions/Degradation.py
txtbcGen/reactions/MassAction.py
txtbcGen/reactions/MichaelisMenten.py
txtbcGen/reactions/MichaelisMentenGeneral.py
txtbcGen/reactions/Reactions.py
txtbcGen/reactions/Synthesis.py
txtbcGen/reactions/__init__.py
txtbcGen-0.0.5.dist-info/METADATA
txtbcGen-0.0.5.dist-info/WHEEL
txtbcGen-0.0.5.dist-info/top_level.txt
txtbcGen-0.0.5.dist-info/RECORD
