Metadata-Version: 2.1
Name: txtbcGen
Version: 0.0.5
Summary: The first few uploads of the txtbcGen package
Home-page: UNKNOWN
Author: Yunduo Lan
Author-email: l810577993@gmail.com
License: UNKNOWN
Keywords: python,txtbc
Platform: UNKNOWN
Classifier: Development Status :: 3 - Alpha
Classifier: Intended Audience :: Education
Classifier: Programming Language :: Python :: 3
Classifier: Operating System :: MacOS :: MacOS X
Classifier: Operating System :: Microsoft :: Windows
